idd/__init__.py
idd/__main__.py
idd/cli.py
idd/diff_driver.py
idd/differ.py
idd/driver.py
idd/layout.tcss
idd/py.typed
idd/debuggers/__init__.py
idd/debuggers/gdb/__init__.py
idd/debuggers/gdb/gdb_commands.py
idd/debuggers/gdb/gdb_driver.py
idd/debuggers/gdb/gdb_mi_driver.py
idd/debuggers/gdb/idd_gdb_controller.py
idd/debuggers/gdb/utils.py
idd/debuggers/lldb/__init__.py
idd/debuggers/lldb/lldb_commands.py
idd/debuggers/lldb/lldb_controller.py
idd/debuggers/lldb/lldb_driver.py
idd/debuggers/lldb/lldb_extensions.py
idd/debuggers/lldb/lldb_new_driver.py
idd/ui/__init__.py
idd/ui/diff_area.py
idd/ui/figlet_text.py
idd/ui/footer.py
idd/ui/header.py
idd/ui/scroll_window.py
idd/ui/scrollable_area.py
idd-1.1.0.dist-info/METADATA
idd-1.1.0.dist-info/WHEEL
idd-1.1.0.dist-info/entry_points.txt
idd-1.1.0.dist-info/licenses/LICENSE
idd-1.1.0.dist-info/RECORD
