Metadata-Version: 2.4
Name: idd
Version: 1.1.0
Summary: A tool for performing interactive dynamic differential debugging capable to identify functional and performance regressions.
Author: Martin Vassilev, Vassil Vassilev, Alexander Penev
License-File: LICENSE
Requires-Python: >=3.9
Requires-Dist: pygdbmi
Requires-Dist: rich
Requires-Dist: textual
